dextools_python/__init__.py
dextools_python/async_dextools_v1.py
dextools_python/async_dextools_v2.py
dextools_python/dextools_v1.py
dextools_python/dextools_v2.py
dextools_python-0.3.2.dist-info/LICENSE.md
dextools_python-0.3.2.dist-info/METADATA
dextools_python-0.3.2.dist-info/WHEEL
dextools_python-0.3.2.dist-info/RECORD
