Metadata-Version: 2.1
Name: dextools-python
Version: 0.3.2
Summary: A simple Python API wrapper for DEXTools
Home-page: https://github.com/alb2001/dextools-python
License: MIT
Keywords: dextools,api,wrapper,blockchain,trading,exchange,uniswap
Author: alb2001
Author-email: alb2001@outlook.es
Requires-Python: >=3.8,<4.0
Classifier: License :: OSI Approved :: MIT License
Classifier: Programming Language :: Python :: 3
Classifier: Programming Language :: Python :: 3.8
Classifier: Programming Language :: Python :: 3.9
Classifier: Programming Language :: Python :: 3.10
Classifier: Programming Language :: Python :: 3.11
Classifier: Programming Language :: Python :: 3.12
Classifier: Programming Language :: Python :: 3.13
Requires-Dist: aiohttp (>=3.9.3,<4.0.0)
Requires-Dist: requests (>=2.31.0,<3.0.0)
Project-URL: Repository, https://github.com/alb2001/dextools-python
